proc_limiter.py
proc_limiter-0.3.1.dist-info/DESCRIPTION.rst
proc_limiter-0.3.1.dist-info/entry_points.txt
proc_limiter-0.3.1.dist-info/METADATA
proc_limiter-0.3.1.dist-info/metadata.json
proc_limiter-0.3.1.dist-info/RECORD
proc_limiter-0.3.1.dist-info/top_level.txt
proc_limiter-0.3.1.dist-info/WHEEL
