Metadata-Version: 2.0
Name: proc-limiter
Version: 0.3.1
Summary: limit instances of given process to specified quantity
Home-page: http://github.com/mysz/proc-limiter
Author: Marcin Sztolcman
Author-email: marcin@urzenia.net
License: MIT
Keywords: limiter processes management
Platform: UNKNOWN
Classifier: Development Status :: 4 - Beta
Classifier: Environment :: Console
Classifier: Intended Audience :: Developers
Classifier: Intended Audience :: Other Audience
Classifier: Intended Audience :: System Administrators
Classifier: License :: OSI Approved :: MIT License
Classifier: Topic :: Utilities
Classifier: Programming Language :: Python :: 3.3
Classifier: Programming Language :: Python :: 3.4
Requires-Dist: argparse
